src/__init__.py
src/kernel.py
src/main.py
src/svgelements.py
src/core/__init__.py
src/core/cutcode.py
src/core/cutplanner.py
src/core/elements.py
src/core/inkscape.py
src/core/plotplanner.py
src/core/rasterplotter.py
src/core/svg_io.py
src/core/webhelp.py
src/core/zinglplotter.py
src/device/__init__.py
src/device/basedevice.py
src/device/lasercommandconstants.py
src/device/ch341/__init__.py
src/device/ch341/ch341.py
src/device/ch341/ch341libusbdriver.py
src/device/ch341/libusb.py
src/device/ch341/mock.py
src/device/ch341/windll.py
src/device/lhystudios/__init__.py
src/device/lhystudios/laserspeed.py
src/device/lhystudios/lhymicrointerpreter.py
src/device/lhystudios/lhystudiocontroller.py
src/device/lhystudios/lhystudioemulator.py
src/device/lhystudios/lhystudiosdevice.py
src/device/moshi/__init__.py
src/device/moshi/moshiconstants.py
src/device/moshi/moshicontroller.py
src/device/moshi/moshidevice.py
src/device/moshi/moshiinterpreter.py
src/dxf/__init__.py
src/dxf/dxf_io.py
src/gui/__init__.py
src/gui/egvsave.py
src/gui/generalsettings.py
src/gui/icons.py
src/gui/laserrender.py
src/gui/mwindow.py
src/gui/rastersettings.py
src/gui/rasterwizard.py
src/gui/rotarysettings.py
src/gui/silence.py
src/gui/silence_app.py
src/gui/terminal.py
src/gui/traceboundary.py
src/gui/widget.py
src/gui/zmatrix.py
src/image/__init__.py
src/image/imagetools.py
K40Silence-0.0.1.dist-info/LICENSE
K40Silence-0.0.1.dist-info/METADATA
K40Silence-0.0.1.dist-info/WHEEL
K40Silence-0.0.1.dist-info/entry_points.txt
K40Silence-0.0.1.dist-info/top_level.txt
K40Silence-0.0.1.dist-info/zip-safe
K40Silence-0.0.1.dist-info/RECORD
