Metadata-Version: 2.1
Name: K40Silence
Version: 0.0.1
Summary: K40Silence: Whisperer/MeerK40t Hybrid
Home-page: https://github.com/meerk40t/Silence
Author: Tatarize
Author-email: tatarize@gmail.com
License: MIT
Keywords: lasercutter,laser,vector,parser
Platform: UNKNOWN
Classifier: Development Status :: 4 - Beta
Classifier: License :: OSI Approved :: MIT License
Classifier: Operating System :: OS Independent
Classifier: Programming Language :: Python
Classifier: Programming Language :: Python :: 3.6
Classifier: Programming Language :: Python :: 3.7
Classifier: Programming Language :: Python :: 3.8
Classifier: Programming Language :: Python :: 3.9
Classifier: Topic :: Multimedia :: Graphics
Classifier: Topic :: Multimedia :: Graphics :: Editors :: Vector-Based
Classifier: Topic :: Utilities
Requires-Dist: pyusb (>=1.0.0)
Provides-Extra: all
Requires-Dist: wxPython (>=4.0.0) ; extra == 'all'
Requires-Dist: Pillow (>=7.0.0) ; extra == 'all'
Requires-Dist: ezdxf (>=0.13.0) ; extra == 'all'
Provides-Extra: dxf
Requires-Dist: ezdxf (>=0.13.0) ; extra == 'dxf'
Provides-Extra: gui
Requires-Dist: wxPython (>=4.0.0) ; extra == 'gui'
Requires-Dist: Pillow (>=7.0.0) ; extra == 'gui'
